LICENSE.txt
MANIFEST.in
README.md
README.rst
contributors.txt
cykdtree_logo.png
cykdtree_logo.svg
setup.cfg
setup.py
cykdtree/__init__.py
cykdtree/c_kdtree.cpp
cykdtree/c_kdtree.hpp
cykdtree/c_parallel_kdtree.cpp
cykdtree/c_parallel_kdtree.hpp
cykdtree/c_utils.cpp
cykdtree/c_utils.hpp
cykdtree/kdtree.cpp
cykdtree/kdtree.pxd
cykdtree/kdtree.pyx
cykdtree/parallel_kdtree.cpp
cykdtree/parallel_kdtree.pxd
cykdtree/parallel_kdtree.pyx
cykdtree/utils.cpp
cykdtree/utils.pxd
cykdtree/utils.pyx
cykdtree.egg-info/PKG-INFO
cykdtree.egg-info/SOURCES.txt
cykdtree.egg-info/dependency_links.txt
cykdtree.egg-info/not-zip-safe
cykdtree.egg-info/top_level.txt
cykdtree/tests/__init__.py
cykdtree/tests/test_kdtree.py
cykdtree/tests/test_parallel_kdtree.py
cykdtree/tests/test_utils.py
docs/Makefile
docs/source/code.rst
docs/source/conf.py
docs/source/index.rst
docs/source/install.rst